jsonriver/__init__.py
jsonriver/parse.py
jsonriver/tokenize.py
jsonriver-1.0.0.dist-info/METADATA
jsonriver-1.0.0.dist-info/WHEEL
jsonriver-1.0.0.dist-info/licenses/LICENSE
jsonriver-1.0.0.dist-info/RECORD
