Metadata-Version: 2.4
Name: jsonriver
Version: 1.0.0
Summary: Streaming JSON parser that yields progressively complete values - Python port of the TypeScript jsonriver library
Project-URL: Homepage, https://github.com/rictic/jsonriver
Project-URL: Documentation, https://github.com/rictic/jsonriver
Project-URL: Repository, https://github.com/yourusername/jsonriver-python
Project-URL: Original TypeScript, https://github.com/rictic/jsonriver
Author: jsonriver-python contributors
License: BSD-3-Clause
License-File: LICENSE
Keywords: async,incremental,json,parser,streaming
Classifier: Development Status :: 5 - Production/Stable
Classifier: Intended Audience :: Developers
Classifier: License :: OSI Approved :: BSD License
Classifier: Programming Language :: Python :: 3
Classifier: Programming Language :: Python :: 3.11
Classifier: Programming Language :: Python :: 3.12
Classifier: Topic :: Software Development :: Libraries :: Python Modules
Classifier: Topic :: Text Processing
Classifier: Typing :: Typed
Requires-Python: >=3.11
Provides-Extra: dev
Requires-Dist: mypy>=1.8.0; extra == 'dev'
Requires-Dist: pytest-asyncio>=0.23.0; extra == 'dev'
Requires-Dist: pytest>=8.0.0; extra == 'dev'
